Metadata-Version: 2.1
Name: vatnumber-xtra
Version: 1.4.1
Summary: Python module to validate VAT numbers
Home-page: http://code.google.com/p/vatnumber/
Author: ximepa
Author-email: xim.michael@gmail.com
License: GPL-3
Download-URL: http://code.google.com/p/vatnumber/downloads/
Platform: UNKNOWN
Classifier: Development Status :: 5 - Production/Stable
Classifier: Intended Audience :: Developers
Classifier: License :: OSI Approved :: GNU General Public License (GPL)
Classifier: Operating System :: OS Independent
Classifier: Programming Language :: Python :: 3
Classifier: Topic :: Office/Business :: Financial :: Accounting
Classifier: Topic :: Software Development :: Internationalization
Classifier: Topic :: Software Development :: Libraries :: Python Modules
Provides-Extra: suds
